corellium_api/__init__.py
corellium_api/api_client.py
corellium_api/configuration.py
corellium_api/exceptions.py
corellium_api/rest.py
corellium_api/api/__init__.py
corellium_api/api/corellium_api.py
corellium_api/models/__init__.py
corellium_api/models/address.py
corellium_api/models/agent_app.py
corellium_api/models/agent_app_ready_response.py
corellium_api/models/agent_app_status.py
corellium_api/models/agent_apps_list.py
corellium_api/models/agent_apps_status_list.py
corellium_api/models/agent_error.py
corellium_api/models/agent_icons.py
corellium_api/models/agent_install_body.py
corellium_api/models/agent_profiles_return.py
corellium_api/models/agent_system_adb_auth.py
corellium_api/models/agent_system_get_prop_body.py
corellium_api/models/agent_value_return.py
corellium_api/models/agreed_ack.py
corellium_api/models/api_conflict_error.py
corellium_api/models/api_error.py
corellium_api/models/api_internal_consistency_error.py
corellium_api/models/api_not_found_error.py
corellium_api/models/api_token.py
corellium_api/models/bit.py
corellium_api/models/btrace_enable_options.py
corellium_api/models/button.py
corellium_api/models/coupon_options.py
corellium_api/models/create_team.py
corellium_api/models/created_by.py
corellium_api/models/credentials.py
corellium_api/models/domain_options.py
corellium_api/models/extension.py
corellium_api/models/features.py
corellium_api/models/file_changes.py
corellium_api/models/firmware.py
corellium_api/models/gpio_state_definition.py
corellium_api/models/gpios_state.py
corellium_api/models/grant_trial_request_response.py
corellium_api/models/hook.py
corellium_api/models/image.py
corellium_api/models/instance.py
corellium_api/models/instance_agent_state.py
corellium_api/models/instance_boot_options.py
corellium_api/models/instance_boot_options_additional_tag.py
corellium_api/models/instance_console_endpoint.py
corellium_api/models/instance_create_options.py
corellium_api/models/instance_input.py
corellium_api-0.3.2.dist-info/METADATA
corellium_api-0.3.2.dist-info/WHEEL
corellium_api-0.3.2.dist-info/top_level.txt
corellium_api-0.3.2.dist-info/RECORD
