Metadata-Version: 2.1
Name: corellium-api
Version: 0.3.2
Summary: Corellium API
Home-page: 
Author: OpenAPI Generator community
Author-email: team@openapitools.org
Keywords: OpenAPI,OpenAPI-Generator,Corellium API
Requires-Dist: urllib3 (>=1.25.3)
Requires-Dist: six (>=1.10)
Requires-Dist: python-dateutil
Requires-Dist: aiohttp (>=3.0.0)
